yellowbox_mssql/__init__.py
yellowbox_mssql/_version.py
yellowbox_mssql-0.1.0.dist-info/LICENSE
yellowbox_mssql-0.1.0.dist-info/METADATA
yellowbox_mssql-0.1.0.dist-info/WHEEL
yellowbox_mssql-0.1.0.dist-info/RECORD
