Metadata-Version: 2.3
Name: yellowbox-mssql
Version: 0.1.0
Summary: 
Author: Biocatch Ltd
Author-email: info@biocatch.com
Requires-Python: >=3.9,<4.0
Classifier: Programming Language :: Python :: 3
Classifier: Programming Language :: Python :: 3.9
Classifier: Programming Language :: Python :: 3.10
Classifier: Programming Language :: Python :: 3.11
Classifier: Programming Language :: Python :: 3.12
Classifier: Programming Language :: Python :: 3.13
Requires-Dist: sqlalchemy (>=1.3.0)
Requires-Dist: sqlalchemy-utils (>=0.38.2)
Requires-Dist: yellowbox (>=0.8.0)
